test_setup_test/__init__.py
test_setup_test/module1.py
test_setup_test-1.0.30.dist-info/METADATA
test_setup_test-1.0.30.dist-info/WHEEL
test_setup_test-1.0.30.dist-info/top_level.txt
test_setup_test-1.0.30.dist-info/RECORD
